{
  "/_not-found/page": "app/_not-found/page.js",
  "/analytics/page": "app/analytics/page.js",
  "/api/auth/[...nextauth]/route": "app/api/auth/[...nextauth]/route.js",
  "/auth/signin/page": "app/auth/signin/page.js",
  "/bulletin-boards/page": "app/bulletin-boards/page.js",
  "/chatrooms/[id]/page": "app/chatrooms/[id]/page.js",
  "/chatrooms/create/page": "app/chatrooms/create/page.js",
  "/chatrooms/page": "app/chatrooms/page.js",
  "/content-generation/page": "app/content-generation/page.js",
  "/dashboard/page": "app/dashboard/page.js",
  "/dev-auth/page": "app/dev-auth/page.js",
  "/location-settings/page": "app/location-settings/page.js",
  "/login/page": "app/login/page.js",
  "/manifest.json/route": "app/manifest.json/route.js",
  "/matches/page": "app/matches/page.js",
  "/messages/page": "app/messages/page.js",
  "/nearby/page": "app/nearby/page.js",
  "/page": "app/page.js",
  "/photos/page": "app/photos/page.js",
  "/profile/page": "app/profile/page.js",
  "/proximity-chatrooms/[id]/page": "app/proximity-chatrooms/[id]/page.js",
  "/recommendations/page": "app/recommendations/page.js",
  "/proximity-chatrooms/page": "app/proximity-chatrooms/page.js",
  "/register-simple/page": "app/register-simple/page.js",
  "/register/page": "app/register/page.js",
  "/test-auth/page": "app/test-auth/page.js",
  "/websocket/page": "app/websocket/page.js"
}