{"version":1,"sessionId":"019eefaf-b346-7ef3-82cf-bd21fc7724d6","savedAt":1782167474610,"widget":{"version":1,"sessionLanguages":[],"files":[{"filePath":"C:/Users/hyper/workspace/fwber/fwber-frontend/app/globals.css","runners":[["lsp",{"status":"succeeded","count":0,"durationMs":15}],["stylelint",{"status":"succeeded","count":0,"durationMs":3924}]],"formatters":[],"diagnostics":[],"allDiagnostics":[],"diagnosticCounts":{"blocking":0,"errors":0,"warnings":0},"hasFinalDiagnosticsSnapshot":false,"touchedAt":1782166066702},{"filePath":"C:\\Users\\hyper\\workspace\\fwber\\fwber-frontend\\app\\globals.css","runners":[],"formatters":[["prettier",{"changed":true,"success":true}]],"diagnostics":[],"allDiagnostics":[],"diagnosticCounts":{"blocking":0,"errors":0,"warnings":0},"hasFinalDiagnosticsSnapshot":true,"touchedAt":1782167226571},{"filePath":"C:/Users/hyper/workspace/fwber/fwber-frontend/tailwind.config.ts","runners":[["tree-sitter",{"status":"skipped","count":0,"durationMs":93}],["fact-rules",{"status":"succeeded","count":0,"durationMs":74}],["ast-grep-napi",{"status":"succeeded","count":0,"durationMs":159}],["lsp",{"status":"succeeded","count":0,"durationMs":1291}],["eslint",{"status":"succeeded","count":0,"durationMs":5923}]],"formatters":[],"diagnostics":[],"allDiagnostics":[],"diagnosticCounts":{"blocking":0,"errors":0,"warnings":0},"hasFinalDiagnosticsSnapshot":false,"touchedAt":1782166094450},{"filePath":"C:\\Users\\hyper\\workspace\\fwber\\fwber-frontend\\tailwind.config.ts","runners":[],"formatters":[["prettier",{"changed":true,"success":true}]],"diagnostics":[],"allDiagnostics":[],"diagnosticCounts":{"blocking":0,"errors":0,"warnings":0},"hasFinalDiagnosticsSnapshot":true,"touchedAt":1782167226486},{"filePath":"C:/Users/hyper/workspace/fwber/fwber-frontend/components/ui/card.tsx","runners":[["tree-sitter",{"status":"skipped","count":0,"durationMs":61}],["fact-rules",{"status":"succeeded","count":0,"durationMs":55}],["ast-grep-napi",{"status":"succeeded","count":0,"durationMs":41}],["lsp",{"status":"succeeded","count":0,"durationMs":1082}],["eslint",{"status":"succeeded","count":0,"durationMs":3845}]],"formatters":[],"diagnostics":[],"allDiagnostics":[],"diagnosticCounts":{"blocking":0,"errors":0,"warnings":0},"hasFinalDiagnosticsSnapshot":false,"touchedAt":1782166140558},{"filePath":"C:\\Users\\hyper\\workspace\\fwber\\fwber-frontend\\components\\ui\\card.tsx","runners":[],"formatters":[["prettier",{"changed":true,"success":true}]],"diagnostics":[],"allDiagnostics":[],"diagnosticCounts":{"blocking":0,"errors":0,"warnings":0},"hasFinalDiagnosticsSnapshot":true,"touchedAt":1782167226674},{"filePath":"C:/Users/hyper/workspace/fwber/fwber-frontend/components/ui/button.tsx","runners":[["tree-sitter",{"status":"skipped","count":0,"durationMs":44}],["fact-rules",{"status":"succeeded","count":0,"durationMs":39}],["ast-grep-napi",{"status":"succeeded","count":0,"durationMs":28}],["lsp",{"status":"succeeded","count":0,"durationMs":1071}],["eslint",{"status":"succeeded","count":0,"durationMs":3598}]],"formatters":[],"diagnostics":[],"allDiagnostics":[],"diagnosticCounts":{"blocking":0,"errors":0,"warnings":0},"hasFinalDiagnosticsSnapshot":false,"touchedAt":1782166174848},{"filePath":"C:\\Users\\hyper\\workspace\\fwber\\fwber-frontend\\components\\ui\\button.tsx","runners":[],"formatters":[["prettier",{"changed":true,"success":true}]],"diagnostics":[],"allDiagnostics":[],"diagnosticCounts":{"blocking":0,"errors":0,"warnings":0},"hasFinalDiagnosticsSnapshot":true,"touchedAt":1782167226540},{"filePath":"C:/Users/hyper/workspace/fwber/fwber-frontend/components/ui/badge.tsx","runners":[["tree-sitter",{"status":"skipped","count":0,"durationMs":38}],["fact-rules",{"status":"succeeded","count":0,"durationMs":34}],["ast-grep-napi",{"status":"succeeded","count":0,"durationMs":24}],["lsp",{"status":"succeeded","count":0,"durationMs":1055}],["eslint",{"status":"succeeded","count":0,"durationMs":3292}]],"formatters":[],"diagnostics":[],"allDiagnostics":[],"diagnosticCounts":{"blocking":0,"errors":0,"warnings":0},"hasFinalDiagnosticsSnapshot":false,"touchedAt":1782166207337},{"filePath":"C:\\Users\\hyper\\workspace\\fwber\\fwber-frontend\\components\\ui\\badge.tsx","runners":[],"formatters":[["prettier",{"changed":true,"success":true}]],"diagnostics":[],"allDiagnostics":[],"diagnosticCounts":{"blocking":0,"errors":0,"warnings":0},"hasFinalDiagnosticsSnapshot":true,"touchedAt":1782167226449},{"filePath":"C:/Users/hyper/workspace/fwber/fwber-frontend/components/ui/dialog.tsx","runners":[["tree-sitter",{"status":"skipped","count":0,"durationMs":52}],["fact-rules",{"status":"succeeded","count":0,"durationMs":44}],["ast-grep-napi",{"status":"succeeded","count":0,"durationMs":28}],["lsp",{"status":"succeeded","count":0,"durationMs":1077}],["eslint",{"status":"succeeded","count":0,"durationMs":3541}]],"formatters":[],"diagnostics":[],"allDiagnostics":[],"diagnosticCounts":{"blocking":0,"errors":0,"warnings":0},"hasFinalDiagnosticsSnapshot":false,"touchedAt":1782166241312},{"filePath":"C:\\Users\\hyper\\workspace\\fwber\\fwber-frontend\\components\\ui\\dialog.tsx","runners":[],"formatters":[["prettier",{"changed":true,"success":true}]],"diagnostics":[],"allDiagnostics":[],"diagnosticCounts":{"blocking":0,"errors":0,"warnings":0},"hasFinalDiagnosticsSnapshot":true,"touchedAt":1782167226608},{"filePath":"C:/Users/hyper/workspace/fwber/fwber-frontend/components/ui/input.tsx","runners":[["tree-sitter",{"status":"skipped","count":0,"durationMs":29}],["fact-rules",{"status":"succeeded","count":0,"durationMs":26}],["ast-grep-napi",{"status":"succeeded","count":0,"durationMs":20}],["lsp",{"status":"succeeded","count":0,"durationMs":1053}],["eslint",{"status":"succeeded","count":0,"durationMs":3250}]],"formatters":[],"diagnostics":[],"allDiagnostics":[],"diagnosticCounts":{"blocking":0,"errors":0,"warnings":0},"hasFinalDiagnosticsSnapshot":false,"touchedAt":1782166275537},{"filePath":"C:/Users/hyper/workspace/fwber/fwber-frontend/components/ui/skeleton.tsx","runners":[["tree-sitter",{"status":"skipped","count":0,"durationMs":32}],["fact-rules",{"status":"succeeded","count":0,"durationMs":28}],["ast-grep-napi",{"status":"succeeded","count":0,"durationMs":23}],["lsp",{"status":"succeeded","count":0,"durationMs":1050}],["eslint",{"status":"succeeded","count":0,"durationMs":3267}]],"formatters":[],"diagnostics":[],"allDiagnostics":[],"diagnosticCounts":{"blocking":0,"errors":0,"warnings":0},"hasFinalDiagnosticsSnapshot":false,"touchedAt":1782166275608},{"filePath":"C:\\Users\\hyper\\workspace\\fwber\\fwber-frontend\\components\\ui\\input.tsx","runners":[],"formatters":[["prettier",{"changed":true,"success":true}]],"diagnostics":[],"allDiagnostics":[],"diagnosticCounts":{"blocking":0,"errors":0,"warnings":0},"hasFinalDiagnosticsSnapshot":true,"touchedAt":1782167226744},{"filePath":"C:\\Users\\hyper\\workspace\\fwber\\fwber-frontend\\components\\ui\\skeleton.tsx","runners":[],"formatters":[["prettier",{"changed":true,"success":true}]],"diagnostics":[],"allDiagnostics":[],"diagnosticCounts":{"blocking":0,"errors":0,"warnings":0},"hasFinalDiagnosticsSnapshot":true,"touchedAt":1782167226587},{"filePath":"C:/Users/hyper/workspace/fwber/fwber-frontend/components/Logo.tsx","runners":[["tree-sitter",{"status":"skipped","count":0,"durationMs":31}],["fact-rules",{"status":"succeeded","count":0,"durationMs":25}],["ast-grep-napi",{"status":"succeeded","count":0,"durationMs":16}],["lsp",{"status":"succeeded","count":0,"durationMs":677}],["eslint",{"status":"succeeded","count":0,"durationMs":3617}],["ts-lsp",{"status":"skipped","count":0,"durationMs":16}],["oxlint",{"status":"skipped","count":0,"durationMs":7}],["biome-check-json",{"status":"skipped","count":0,"durationMs":7}]],"formatters":[],"diagnostics":[],"allDiagnostics":[],"diagnosticCounts":{"blocking":0,"errors":0,"warnings":0},"hasFinalDiagnosticsSnapshot":false,"touchedAt":1782166398870},{"filePath":"C:\\Users\\hyper\\workspace\\fwber\\fwber-frontend\\components\\Logo.tsx","runners":[],"formatters":[["prettier",{"changed":true,"success":true}]],"diagnostics":[],"allDiagnostics":[],"diagnosticCounts":{"blocking":0,"errors":0,"warnings":0},"hasFinalDiagnosticsSnapshot":true,"touchedAt":1782167226557},{"filePath":"C:/Users/hyper/workspace/fwber/fwber-frontend/components/landing/LandingVariantA.tsx","runners":[["tree-sitter",{"status":"skipped","count":0,"durationMs":117}],["fact-rules",{"status":"succeeded","count":0,"durationMs":111}],["ast-grep-napi",{"status":"succeeded","count":0,"durationMs":54}],["lsp",{"status":"succeeded","count":0,"durationMs":1149}],["eslint",{"status":"succeeded","count":0,"durationMs":3909}]],"formatters":[],"diagnostics":[],"allDiagnostics":[],"diagnosticCounts":{"blocking":0,"errors":0,"warnings":0},"hasFinalDiagnosticsSnapshot":false,"touchedAt":1782166449593},{"filePath":"C:\\Users\\hyper\\workspace\\fwber\\fwber-frontend\\components\\landing\\LandingVariantA.tsx","runners":[],"formatters":[["prettier",{"changed":true,"success":true}]],"diagnostics":[],"allDiagnostics":[],"diagnosticCounts":{"blocking":0,"errors":0,"warnings":0},"hasFinalDiagnosticsSnapshot":true,"touchedAt":1782167227056},{"filePath":"C:/Users/hyper/workspace/fwber/fwber-frontend/app/dashboard/page.tsx","runners":[["tree-sitter",{"status":"skipped","count":0,"durationMs":145}],["fact-rules",{"status":"succeeded","count":5,"durationMs":141}],["ast-grep-napi",{"status":"succeeded","count":0,"durationMs":76}],["lsp",{"status":"succeeded","count":0,"durationMs":1197}],["eslint",{"status":"succeeded","count":0,"durationMs":5050}]],"formatters":[],"diagnostics":[],"allDiagnostics":[],"diagnosticCounts":{"blocking":0,"errors":0,"warnings":0},"hasFinalDiagnosticsSnapshot":false,"touchedAt":1782166519148},{"filePath":"C:\\Users\\hyper\\workspace\\fwber\\fwber-frontend\\app\\dashboard\\page.tsx","runners":[],"formatters":[["prettier",{"changed":true,"success":true}]],"diagnostics":[{"severity":"warning","semantic":"warning","message":"'DashboardPage' has cyclomatic complexity 24 — consider breaking it up","line":78,"col":1,"rule":"high-complexity","tool":"high-complexity","uri":"file:///C:/Users/hyper/workspace/fwber/fwber-frontend/app/dashboard/page.tsx#L78:1"},{"severity":"warning","semantic":"warning","message":"String literal \"h-5 w-5\" repeated 67 times — extract to a named constant","line":135,"col":1,"rule":"duplicate-string-literal","tool":"duplicate-string-literal","uri":"file:///C:/Users/hyper/workspace/fwber/fwber-frontend/app/dashboard/page.tsx#L135:1"},{"severity":"warning","semantic":"warning","message":"String literal \"green\" repeated 11 times — extract to a named constant","line":137,"col":1,"rule":"duplicate-string-literal","tool":"duplicate-string-literal","uri":"file:///C:/Users/hyper/workspace/fwber/fwber-frontend/app/dashboard/page.tsx#L137:1"},{"severity":"warning","semantic":"warning","message":"String literal \"purple\" repeated 13 times — extract to a named constant","line":138,"col":1,"rule":"duplicate-string-literal","tool":"duplicate-string-literal","uri":"file:///C:/Users/hyper/workspace/fwber/fwber-frontend/app/dashboard/page.tsx#L138:1"},{"severity":"warning","semantic":"warning","message":"String literal \"h-4 w-4\" repeated 16 times — extract to a named constant","line":163,"col":1,"rule":"duplicate-string-literal","tool":"duplicate-string-literal","uri":"file:///C:/Users/hyper/workspace/fwber/fwber-frontend/app/dashboard/page.tsx#L163:1"}],"allDiagnostics":[{"severity":"warning","semantic":"warning","message":"'DashboardPage' has cyclomatic complexity 24 — consider breaking it up","line":78,"col":1,"rule":"high-complexity","tool":"high-complexity","uri":"file:///C:/Users/hyper/workspace/fwber/fwber-frontend/app/dashboard/page.tsx#L78:1"},{"severity":"warning","semantic":"warning","message":"String literal \"h-5 w-5\" repeated 67 times — extract to a named constant","line":135,"col":1,"rule":"duplicate-string-literal","tool":"duplicate-string-literal","uri":"file:///C:/Users/hyper/workspace/fwber/fwber-frontend/app/dashboard/page.tsx#L135:1"},{"severity":"warning","semantic":"warning","message":"String literal \"green\" repeated 11 times — extract to a named constant","line":137,"col":1,"rule":"duplicate-string-literal","tool":"duplicate-string-literal","uri":"file:///C:/Users/hyper/workspace/fwber/fwber-frontend/app/dashboard/page.tsx#L137:1"},{"severity":"warning","semantic":"warning","message":"String literal \"purple\" repeated 13 times — extract to a named constant","line":138,"col":1,"rule":"duplicate-string-literal","tool":"duplicate-string-literal","uri":"file:///C:/Users/hyper/workspace/fwber/fwber-frontend/app/dashboard/page.tsx#L138:1"},{"severity":"warning","semantic":"warning","message":"String literal \"h-4 w-4\" repeated 16 times — extract to a named constant","line":163,"col":1,"rule":"duplicate-string-literal","tool":"duplicate-string-literal","uri":"file:///C:/Users/hyper/workspace/fwber/fwber-frontend/app/dashboard/page.tsx#L163:1"}],"diagnosticCounts":{"blocking":0,"errors":0,"warnings":5},"hasFinalDiagnosticsSnapshot":true,"touchedAt":1782167227113},{"filePath":"C:/Users/hyper/workspace/fwber/fwber-frontend/components/ThemeToggle.tsx","runners":[["tree-sitter",{"status":"skipped","count":0,"durationMs":47}],["fact-rules",{"status":"succeeded","count":0,"durationMs":42}],["ast-grep-napi",{"status":"succeeded","count":0,"durationMs":33}],["lsp",{"status":"succeeded","count":0,"durationMs":1071}],["eslint",{"status":"succeeded","count":0,"durationMs":4889}]],"formatters":[],"diagnostics":[],"allDiagnostics":[],"diagnosticCounts":{"blocking":0,"errors":0,"warnings":0},"hasFinalDiagnosticsSnapshot":false,"touchedAt":1782166557153},{"filePath":"C:\\Users\\hyper\\workspace\\fwber\\fwber-frontend\\components\\ThemeToggle.tsx","runners":[],"formatters":[["prettier",{"changed":true,"success":true}]],"diagnostics":[],"allDiagnostics":[],"diagnosticCounts":{"blocking":0,"errors":0,"warnings":0},"hasFinalDiagnosticsSnapshot":true,"touchedAt":1782167226362},{"filePath":"C:/Users/hyper/workspace/fwber/fwber-frontend/components/AppHeader.tsx","runners":[["tree-sitter",{"status":"skipped","count":0,"durationMs":119}],["fact-rules",{"status":"succeeded","count":3,"durationMs":110}],["ast-grep-napi",{"status":"succeeded","count":0,"durationMs":59}],["lsp",{"status":"succeeded","count":0,"durationMs":1169}],["eslint",{"status":"succeeded","count":0,"durationMs":5633}]],"formatters":[],"diagnostics":[],"allDiagnostics":[],"diagnosticCounts":{"blocking":0,"errors":0,"warnings":0},"hasFinalDiagnosticsSnapshot":false,"touchedAt":1782166626957},{"filePath":"C:\\Users\\hyper\\workspace\\fwber\\fwber-frontend\\components\\AppHeader.tsx","runners":[],"formatters":[["prettier",{"changed":true,"success":true}]],"diagnostics":[{"severity":"warning","semantic":"warning","message":"Function 'shouldUseHardNavigation' is a trivial pass-through wrapper","line":73,"col":1,"rule":"pass-through-wrappers","tool":"pass-through-wrappers","uri":"file:///C:/Users/hyper/workspace/fwber/fwber-frontend/components/AppHeader.tsx#L73:1"},{"severity":"warning","semantic":"warning","message":"'AppHeader' has cyclomatic complexity 26 — consider breaking it up","line":191,"col":1,"rule":"high-complexity","tool":"high-complexity","uri":"file:///C:/Users/hyper/workspace/fwber/fwber-frontend/components/AppHeader.tsx#L191:1"},{"severity":"warning","semantic":"warning","message":"'AppHeader' calls 25 distinct functions — coordination smell, consider splitting responsibilities","line":191,"col":1,"rule":"high-fan-out","tool":"high-fan-out","uri":"file:///C:/Users/hyper/workspace/fwber/fwber-frontend/components/AppHeader.tsx#L191:1"}],"allDiagnostics":[{"severity":"warning","semantic":"warning","message":"Function 'shouldUseHardNavigation' is a trivial pass-through wrapper","line":73,"col":1,"rule":"pass-through-wrappers","tool":"pass-through-wrappers","uri":"file:///C:/Users/hyper/workspace/fwber/fwber-frontend/components/AppHeader.tsx#L73:1"},{"severity":"warning","semantic":"warning","message":"'AppHeader' has cyclomatic complexity 26 — consider breaking it up","line":191,"col":1,"rule":"high-complexity","tool":"high-complexity","uri":"file:///C:/Users/hyper/workspace/fwber/fwber-frontend/components/AppHeader.tsx#L191:1"},{"severity":"warning","semantic":"warning","message":"'AppHeader' calls 25 distinct functions — coordination smell, consider splitting responsibilities","line":191,"col":1,"rule":"high-fan-out","tool":"high-fan-out","uri":"file:///C:/Users/hyper/workspace/fwber/fwber-frontend/components/AppHeader.tsx#L191:1"}],"diagnosticCounts":{"blocking":0,"errors":0,"warnings":3},"hasFinalDiagnosticsSnapshot":true,"touchedAt":1782167226856},{"filePath":"C:/Users/hyper/workspace/fwber/fwber-frontend/components/GlobalSubpageNav.tsx","runners":[["tree-sitter",{"status":"skipped","count":0,"durationMs":57}],["fact-rules",{"status":"succeeded","count":0,"durationMs":49}],["ast-grep-napi",{"status":"succeeded","count":0,"durationMs":34}],["lsp",{"status":"succeeded","count":0,"durationMs":1091}],["ts-lsp",{"status":"skipped","count":0,"durationMs":12}],["eslint",{"status":"succeeded","count":0,"durationMs":5407}],["oxlint",{"status":"skipped","count":0,"durationMs":7}],["biome-check-json",{"status":"skipped","count":0,"durationMs":7}]],"formatters":[],"diagnostics":[],"allDiagnostics":[],"diagnosticCounts":{"blocking":0,"errors":0,"warnings":0},"hasFinalDiagnosticsSnapshot":false,"touchedAt":1782166676416},{"filePath":"C:\\Users\\hyper\\workspace\\fwber\\fwber-frontend\\components\\GlobalSubpageNav.tsx","runners":[],"formatters":[["prettier",{"changed":true,"success":true}]],"diagnostics":[],"allDiagnostics":[],"diagnosticCounts":{"blocking":0,"errors":0,"warnings":0},"hasFinalDiagnosticsSnapshot":true,"touchedAt":1782167226422}]}}